Workbook

Sheet Produits
A1: SKU | B1: Nom Produit | C1: Stock Actuel | D1: Ventes Totales (30j) | E1: Ventes/Jour (moy 30j) | F1: Multiplicateur Prévision | G1: Ventes/Jour Ajustées | H1: Fournisseur | I1: leadTimeDays | J1: MOQ | K1: Prix Achat | L1: Prix Vente | M1: Marge Unitiaire | N1: Stock Sécu Custom (jours) | O1: Point Commande | P1: Qté á Commander | Q1: Statut | R1: Investissement | S1: Inventoryvalue
A2: SKU-001 | B2: Nova Max | C2: 162 | D2: 30 | E2: =D2/30 -> 1 | F2: 3 | G2: =E2*F2 -> 3 | H2: Alibaba Express | I2: =IF(H2="","",IF(ISNA(VLOOKUP(H2,Fournisseurs!A:D,3,FALSE)),"",VLOOKUP(H2,Fournisseurs!A:D,3,FALSE))) -> 45 | J2: =IF(H2="","",IF(ISNA(VLOOKUP(H2,Fournisseurs!A:D,4,FALSE)),"",VLOOKUP(H2,Fournisseurs!A:D,4,FALSE))) -> 10 | K2: 8.5 | L2: 24.9 | M2: =L2-K2 -> 16.4 | N2: =I2*0.2 -> 9 | O2: =G2*(I2+N2) -> 162 | P2: =IF(C2<=O2, MAX(J2, O2-C2), 0) -> 10 | Q2: =IF(C2<=O2, "⚠️ COMMANDER", IF(C2<=O2*1.2, "⚡ Surveiller", "✅ OK")) -> ⚠️ COMMANDER | R2: =P2*K2 -> 85 | S2: =C2*K2 -> 1377
A3: SKU-002 | B3: Chromecast | C3: 144 | D3: 40 | E3: =D3/30 -> 1.3333333 | F3: 2 | G3: =E3*F3 -> 2.6666667 | H3: =IF(ISNA(VLOOKUP(A3,'SKU-Fournisseurs'!A:B,2,FALSE)),"",VLOOKUP(A3,'SKU-Fournisseurs'!A:B,2,FALSE)) -> Alibaba Express | I3: =IF(H3="","",IF(ISNA(VLOOKUP(H3,Fournisseurs!A:D,3,FALSE)),"",VLOOKUP(H3,Fournisseurs!A:D,3,FALSE))) -> 45 | J3: =IF(H3="","",IF(ISNA(VLOOKUP(H3,Fournisseurs!A:D,4,FALSE)),"",VLOOKUP(H3,Fournisseurs!A:D,4,FALSE))) -> 10 | K3: 2.3 | L3: 9.9 | M3: =L3-K3 -> 7.6 | N3: 9 | O3: =G3*(I3+N3) -> 144 | P3: =IF(C3<=O3, MAX(J3, O3-C3), 0) -> 10 | Q3: =IF(C3<=O3, "⚠️ COMMANDER", IF(C3<=O3*1.2, "⚡ Surveiller", "✅ OK")) -> ⚠️ COMMANDER | R3: =P3*K3 -> 23 | S3: =C3*K3 -> 331.2
A4: SKU-003 | B4: Fire Stick 4K | C4: 10 | D4: 13 | E4: =D4/30 -> 0.43333333 | F4: 1 | G4: =E4*F4 -> 0.43333333 | H4: =IF(ISNA(VLOOKUP(A4,'SKU-Fournisseurs'!A:B,2,FALSE)),"",VLOOKUP(A4,'SKU-Fournisseurs'!A:B,2,FALSE)) -> Fournisseur France | I4: =IF(H4="","",IF(ISNA(VLOOKUP(H4,Fournisseurs!A:D,3,FALSE)),"",VLOOKUP(H4,Fournisseurs!A:D,3,FALSE))) -> 10 | J4: =IF(H4="","",IF(ISNA(VLOOKUP(H4,Fournisseurs!A:D,4,FALSE)),"",VLOOKUP(H4,Fournisseurs!A:D,4,FALSE))) -> 50 | K4: 12 | L4: 34.9 | M4: =L4-K4 -> 22.9 | N4: =I4*0.2 -> 2 | O4: =G4*(I4+N4) -> 5.2 | P4: =IF(C4<=O4, MAX(J4, O4-C4), 0) -> 0 | Q4: =IF(C4<=O4, "⚠️ COMMANDER", IF(C4<=O4*1.2, "⚡ Surveiller", "✅ OK")) -> ✅ OK | R4: =P4*K4 -> 0 | S4: =C4*K4 -> 120
A5: SKU-004 | B5: Fire Stick Lite | C5: 10 | D5: 23 | E5: =D5/30 -> 0.76666667 | F5: 1.5 | G5: =E5*F5 -> 1.15 | H5: =IF(ISNA(VLOOKUP(A5,'SKU-Fournisseurs'!A:B,2,FALSE)),"",VLOOKUP(A5,'SKU-Fournisseurs'!A:B,2,FALSE)) -> Fournisseur France | I5: =IF(H5="","",IF(ISNA(VLOOKUP(H5,Fournisseurs!A:D,3,FALSE)),"",VLOOKUP(H5,Fournisseurs!A:D,3,FALSE))) -> 10 | J5: =IF(H5="","",IF(ISNA(VLOOKUP(H5,Fournisseurs!A:D,4,FALSE)),"",VLOOKUP(H5,Fournisseurs!A:D,4,FALSE))) -> 50 | K5: 6.5 | L5: 19.9 | M5: =L5-K5 -> 13.4 | N5: =I5*0.2 -> 2 | O5: =G5*(I5+N5) -> 13.8 | P5: =IF(C5<=O5, MAX(J5, O5-C5), 0) -> 50 | Q5: =IF(C5<=O5, "⚠️ COMMANDER", IF(C5<=O5*1.2, "⚡ Surveiller", "✅ OK")) -> ⚠️ COMMANDER | R5: =P5*K5 -> 325 | S5: =C5*K5 -> 65
A6: SKU-005 | B6: TV Samsung | C6: 10 | D6: 30 | E6: =D6/30 -> 1 | F6: 2 | G6: =E6*F6 -> 2 | H6: =IF(ISNA(VLOOKUP(A6,'SKU-Fournisseurs'!A:B,2,FALSE)),"",VLOOKUP(A6,'SKU-Fournisseurs'!A:B,2,FALSE)) -> Fournisseur Italie | I6: =IF(H6="","",IF(ISNA(VLOOKUP(H6,Fournisseurs!A:D,3,FALSE)),"",VLOOKUP(H6,Fournisseurs!A:D,3,FALSE))) -> 20 | J6: =IF(H6="","",IF(ISNA(VLOOKUP(H6,Fournisseurs!A:D,4,FALSE)),"",VLOOKUP(H6,Fournisseurs!A:D,4,FALSE))) -> 75 | K6: 15 | L6: 44.9 | M6: =L6-K6 -> 29.9 | N6: =I6*0.2 -> 4 | O6: =G6*(I6+N6) -> 48 | P6: =IF(C6<=O6, MAX(J6, O6-C6), 0) -> 75 | Q6: =IF(C6<=O6, "⚠️ COMMANDER", IF(C6<=O6*1.2, "⚡ Surveiller", "✅ OK")) -> ⚠️ COMMANDER | R6: =P6*K6 -> 1125 | S6: =C6*K6 -> 150
A7: SKU-006 | B7: Apple TV Box | C7: 146 | D7: 27 | E7: =D7/30 -> 0.9 | F7: 3 | G7: =E7*F7 -> 2.7 | H7: =IF(ISNA(VLOOKUP(A7,'SKU-Fournisseurs'!A:B,2,FALSE)),"",VLOOKUP(A7,'SKU-Fournisseurs'!A:B,2,FALSE)) -> Alibaba Express | I7: =IF(H7="","",IF(ISNA(VLOOKUP(H7,Fournisseurs!A:D,3,FALSE)),"",VLOOKUP(H7,Fournisseurs!A:D,3,FALSE))) -> 45 | J7: =IF(H7="","",IF(ISNA(VLOOKUP(H7,Fournisseurs!A:D,4,FALSE)),"",VLOOKUP(H7,Fournisseurs!A:D,4,FALSE))) -> 10 | K7: 5.2 | L7: 16.9 | M7: =L7-K7 -> 11.7 | N7: =I7*0.2 -> 9 | O7: =G7*(I7+N7) -> 145.8 | P7: =IF(C7<=O7, MAX(J7, O7-C7), 0) -> 0 | Q7: =IF(C7<=O7, "⚠️ COMMANDER", IF(C7<=O7*1.2, "⚡ Surveiller", "✅ OK")) -> ⚡ Surveiller | R7: =P7*K7 -> 0 | S7: =C7*K7 -> 759.2
A8: SKU-007 | B8: Xiaomi TV | C8: 10 | D8: 10 | E8: =D8/30 -> 0.33333333 | F8: 3 | G8: =E8*F8 -> 1 | H8: =IF(ISNA(VLOOKUP(A8,'SKU-Fournisseurs'!A:B,2,FALSE)),"",VLOOKUP(A8,'SKU-Fournisseurs'!A:B,2,FALSE)) -> Fournisseur Allemagne | I8: =IF(H8="","",IF(ISNA(VLOOKUP(H8,Fournisseurs!A:D,3,FALSE)),"",VLOOKUP(H8,Fournisseurs!A:D,3,FALSE))) -> 15 | J8: =IF(H8="","",IF(ISNA(VLOOKUP(H8,Fournisseurs!A:D,4,FALSE)),"",VLOOKUP(H8,Fournisseurs!A:D,4,FALSE))) -> 60 | K8: 28 | L8: 79.9 | M8: =L8-K8 -> 51.9 | N8: =I8*0.2 -> 3 | O8: =G8*(I8+N8) -> 18 | P8: =IF(C8<=O8, MAX(J8, O8-C8), 0) -> 60 | Q8: =IF(C8<=O8, "⚠️ COMMANDER", IF(C8<=O8*1.2, "⚡ Surveiller", "✅ OK")) -> ⚠️ COMMANDER | R8: =P8*K8 -> 1680 | S8: =C8*K8 -> 280
A9: SKU-008 | B9: Xiamo Box | C9: 10 | D9: 5 | E9: =D9/30 -> 0.16666667 | F9: 1 | G9: =E9*F9 -> 0.16666667 | H9: =IF(ISNA(VLOOKUP(A9,'SKU-Fournisseurs'!A:B,2,FALSE)),"",VLOOKUP(A9,'SKU-Fournisseurs'!A:B,2,FALSE)) -> Fournisseur France | I9: =IF(H9="","",IF(ISNA(VLOOKUP(H9,Fournisseurs!A:D,3,FALSE)),"",VLOOKUP(H9,Fournisseurs!A:D,3,FALSE))) -> 10 | J9: =IF(H9="","",IF(ISNA(VLOOKUP(H9,Fournisseurs!A:D,4,FALSE)),"",VLOOKUP(H9,Fournisseurs!A:D,4,FALSE))) -> 50 | K9: 8.5 | L9: 24.9 | M9: =L9-K9 -> 16.4 | N9: =I9*0.2 -> 2 | O9: =G9*(I9+N9) -> 2 | P9: =IF(C9<=O9, MAX(J9, O9-C9), 0) -> 0 | Q9: =IF(C9<=O9, "⚠️ COMMANDER", IF(C9<=O9*1.2, "⚡ Surveiller", "✅ OK")) -> ✅ OK | R9: =P9*K9 -> 0 | S9: =C9*K9 -> 85
A10: SKU-009 | B10: Airpods Pro | C10: 10 | D10: 17 | E10: =D10/30 -> 0.56666667 | F10: 1 | G10: =E10*F10 -> 0.56666667 | H10: =IF(ISNA(VLOOKUP(A10,'SKU-Fournisseurs'!A:B,2,FALSE)),"",VLOOKUP(A10,'SKU-Fournisseurs'!A:B,2,FALSE)) -> Fournisseur Italie | I10: =IF(H10="","",IF(ISNA(VLOOKUP(H10,Fournisseurs!A:D,3,FALSE)),"",VLOOKUP(H10,Fournisseurs!A:D,3,FALSE))) -> 20 | J10: =IF(H10="","",IF(ISNA(VLOOKUP(H10,Fournisseurs!A:D,4,FALSE)),"",VLOOKUP(H10,Fournisseurs!A:D,4,FALSE))) -> 75 | K10: 18.5 | L10: 54.9 | M10: =L10-K10 -> 36.4 | N10: =I10*0.2 -> 4 | O10: =G10*(I10+N10) -> 13.6 | P10: =IF(C10<=O10, MAX(J10, O10-C10), 0) -> 75 | Q10: =IF(C10<=O10, "⚠️ COMMANDER", IF(C10<=O10*1.2, "⚡ Surveiller", "✅ OK")) -> ⚠️ COMMANDER | R10: =P10*K10 -> 1387.5 | S10: =C10*K10 -> 185
A11: SKU-010 | B11: Iphone 17 Pro Max | C11: 65 | D11: 12 | E11: =D11/30 -> 0.4 | F11: 3 | G11: =E11*F11 -> 1.2 | H11: =IF(ISNA(VLOOKUP(A11,'SKU-Fournisseurs'!A:B,2,FALSE)),"",VLOOKUP(A11,'SKU-Fournisseurs'!A:B,2,FALSE)) -> Alibaba Express | I11: =IF(H11="","",IF(ISNA(VLOOKUP(H11,Fournisseurs!A:D,3,FALSE)),"",VLOOKUP(H11,Fournisseurs!A:D,3,FALSE))) -> 45 | J11: =IF(H11="","",IF(ISNA(VLOOKUP(H11,Fournisseurs!A:D,4,FALSE)),"",VLOOKUP(H11,Fournisseurs!A:D,4,FALSE))) -> 10 | K11: 1.8 | L11: 7.9 | M11: =L11-K11 -> 6.1 | N11: =I11*0.2 -> 9 | O11: =G11*(I11+N11) -> 64.8 | P11: =IF(C11<=O11, MAX(J11, O11-C11), 0) -> 0 | Q11: =IF(C11<=O11, "⚠️ COMMANDER", IF(C11<=O11*1.2, "⚡ Surveiller", "✅ OK")) -> ⚡ Surveiller | R11: =P11*K11 -> 0 | S11: =C11*K11 -> 117

Sheet Commandes
A1: id | B1: supplier | C1: warehouseId | D1: status | E1: total | F1: createdAt | G1: eta | H1: confirmedAt | I1: shippedAt | J1: receivedAt | K1: completedAt | L1: trackingNumber | M1: trackingUrl | N1: hasDiscrepancy | O1: damageReport | P1: notes
A2: PO-311025-1432 | B2: Fournisseur France | C2: Casa Joli | D2: pending_confirmation | E2: 325 | F2: 45961 | N2: FALSE
A3: PO-311025-1444 | B3: Fournisseur France | C3: Casa Joli | D3: pending_confirmation | E3: 325 | F3: 45961 | N3: FALSE
A4: PO-111125-1920 | B4: Alibaba Express | C4: Casa Joli | D4: completed | E4: 2406.4 | F4: 45972 | G4: 46017 | H4: 2025-11-11T18:52:50.119Z | I4: 45972 | J4: 45972 | K4: 45972 | L4: 1ZABC123456789 | M4: https://tracking.fake/PO-111125-1920 | N4: FALSE | O4: FALSE
A5: PO-111125-1950 | B5: Alibaba Express | C5: Casa Joli | D5: pending_confirmation | E5: 2406.4 | F5: 45972 | N5: FALSE
A6: PO-111125-2013 | B6: Alibaba Express | C6: Casa Joli | D6: pending_confirmation | E6: 2406.4 | F6: 45972 | N6: FALSE
A7: PO-111125-2027 | B7: Alibaba Express | C7: Casa Joli | D7: pending_confirmation | E7: 108 | F7: 45972 | N7: FALSE

Sheet ArticlesCommande
A1: orderId | B1: sku | C1: quantity | D1: pricePerUnit | E1: receivedQuantity | F1: discrepancyType | G1: discrepancyQuantity | H1: damagedQuantity | I1: discrepancyNotes
A2: PO-311025-1408 | B2: SKU-007 | C2: 60 | D2: 28 | E2: 0
A3: PO-311025-1432 | B3: SKU-004 | C3: 50 | D3: 6.5 | E3: 0 | G3: 0 | H3: 0
A4: PO-311025-1444 | B4: SKU-004 | C4: 50 | D4: 6.5 | E4: 0 | G4: 0 | H4: 0
A5: PO-111125-1920 | B5: SKU-001 | C5: 152 | D5: 8.5 | E5: 0 | G5: 0 | H5: 0
A6: PO-111125-1920 | B6: SKU-002 | C6: 134 | D6: 2.3 | E6: 0 | G6: 0 | H6: 0
A7: PO-111125-1920 | B7: SKU-006 | C7: 136 | D7: 5.2 | E7: 0 | G7: 0 | H7: 0
A8: PO-111125-1920 | B8: SKU-010 | C8: 55 | D8: 1.8 | E8: 0 | G8: 0 | H8: 0
A9: PO-111125-1950 | B9: SKU-001 | C9: 152 | D9: 8.5 | E9: 0 | G9: 0 | H9: 0
A10: PO-111125-1950 | B10: SKU-002 | C10: 134 | D10: 2.3 | E10: 0 | G10: 0 | H10: 0
A11: PO-111125-1950 | B11: SKU-006 | C11: 136 | D11: 5.2 | E11: 0 | G11: 0 | H11: 0
A12: PO-111125-1950 | B12: SKU-010 | C12: 55 | D12: 1.8 | E12: 0 | G12: 0 | H12: 0
A13: PO-111125-2013 | B13: SKU-001 | C13: 152 | D13: 8.5 | E13: 0 | G13: 0 | H13: 0
A14: PO-111125-2013 | B14: SKU-002 | C14: 134 | D14: 2.3 | E14: 0 | G14: 0 | H14: 0
... A18: PO-111125-2027 | B18: SKU-002 | C18: 10 | D18: 2.3 | E18: 0 | G18: 0 | H18: 0

Sheet Fournisseurs
A1: Nom Fournisseur | B1: Email | C1: leadTimeDays | D1: MOQ Standard | E1: Notes
A2: Alibaba Express | B2: jory.cherief@gmail.com | C2: 45 | D2: 10 | E2: Paiement 30% avance, qualité OK
A3: Fournisseur France | B3: contact@fournisseur.fr | C3: 10 | D3: 50 | E3: Livraison rapide, prix élevés
A4: Fournisseur Italie | B4: info@fornitore.it | C4: 20 | D4: 75 | E4: Qualité premium, délais moyens
A5: Fournisseur Allemagne | B5: hello@lieferant.de | C5: 15 | D5: 60 | E5: Très fiable, certifié

Sheet Parametres
A1: paramName | B1: value | C1: Description
A2: SeuilSurstockProfond | B2: 60 | C2: Nombre de jours d'autonomie définissant un surstock profond (90-120j)
A3: DeviseDefaut | B3: USD | C3: Devise utilisée pour les prix (EUR, USD, GBP, etc.)
A4: MultiplicateurDefaut | B4: 1.2 | C4: Multiplicateur de sécurité par défaut pour les nouveaux produits

Sheet SKU-Fournisseurs
A1: SKU | B1: Fournisseur
A2: SKU-001 | B2: Alibaba Express
A3: SKU-002 | B3: Alibaba Express
A4: SKU-003 | B4: Fournisseur France
A5: SKU-004 | B5: Fournisseur France
A6: SKU-005 | B6: Fournisseur Italie
A7: SKU-006 | B7: Alibaba Express
A8: SKU-007 | B8: Fournisseur Allemagne
A9: SKU-008 | B9: Fournisseur France
A10: SKU-009 | B10: Fournisseur Italie
A11: SKU-010 | B11: Alibaba Express

Sheet Warehouses
A1: name | B1: address | C1: city | D1: postalCode | E1: country | F1: notes
A2: Casa Joli | B2: Passatge de Font, 6 | C2: Barcelona | D2: 8013 | E2: Espagne
A3: Bluespace Albi | B3: 4 Avenue De La Verrerie | C3: Albi | D3: 81000 | E3: France
A4: Bluespace Toulouse | B4: Rue Alsace Lorraine | C4: Toulouse | D4: 31000 | E4: France
A5: Test 4 | B5: Rue Blanche | C5: Paris | D5: 75009 | E5: France
